{
  "data_type": "trading_decision_log",
  "history_file": "decision_logs/trading_log_20260717_173646.json",
  "latest_file": "decision_log.json",
  "log_id": "trading_log_20260717_173646",
  "raw_rows": [
    {
      "action": "HOLD",
      "amount": "",
      "avg_trade_value_20": 19629085817.4725,
      "blocked": "",
      "cash": "",
      "cash_ratio": "",
      "category": "",
      "cooldown_days": "",
      "current_price": 330.375,
      "cyclical_travel_risk_penalty": 0,
      "cyclical_travel_risk_tier": "none",
      "deferred_sell_reason_code": "",
      "distance_from_ma60": 10.960988719310416,
      "event": "SELL_CHECK",
      "excluded_reason": "",
      "excluded_reason_ko": "",
      "gap_percent": -0.3840844985896763,
      "high_52w": null,
      "holding_days": 3,
      "intraday_range_percent": 1.817443494024018,
      "last_sell_date": "",
      "last_sell_reason": "",
      "ma20": 305.34975,
      "ma5": 324.661,
      "ma60": 297.73977666666667,
      "passed": "",
      "position_vs_52w_high_percent": null,
      "previous_day_return": 1.7587786259541938,
      "profit_rate": 2.35,
      "qty": "",
      "rank": "",
      "reason": "no sell condition",
      "reason_ko": "\ub9e4\ub3c4 \uc870\uac74 \uc5c6\uc74c",
      "recent_20d_return": 11.632032437911821,
      "recent_3d_return": 4.927586864003053,
      "recent_5d_return": 4.774514778637573,
      "relative_strength_20_edge": 10.68095316079628,
      "relative_strength_60_edge": 12.208397828776718,
      "relative_strength_positive": true,
      "remaining_cooldown_days": "",
      "score": "",
      "score_breakdown": {
        "avg_trade_value_20": {
          "points": 10,
          "reason": "20-day average trade value >= 1,000,000,000"
        },
        "current_price_above_ma20": {
          "points": 20,
          "reason": "current price > ma20"
        },
        "distance_from_ma60": {
          "points": 10,
          "reason": "distance from ma60 <= 20%"
        },
        "ma_alignment": {
          "points": 30,
          "reason": "ma5 > ma20 > ma60"
        },
        "recent_5d_return": {
          "points": 15,
          "reason": "recent 5-day return <= 5%"
        },
        "relative_strength_vs_qqq": {
          "points": 10,
          "reason": "20/60-day relative strength vs QQQ is positive"
        },
        "volatility_20": {
          "points": 10,
          "reason": "20-day volatility <= 5%"
        }
      },
      "sell_reason_code": null,
      "share_ratio": "",
      "symbol": "AAPL",
      "timestamp": "2026-07-17T17:36:39",
      "today_return": -0.8656904518994146,
      "volatility_20": 2.3078666808193207,
      "volume_spike_ratio": 0.9609415198413622
    },
    {
      "action": "",
      "amount": "",
      "avg_trade_value_20": null,
      "blocked": "",
      "cash": "",
      "cash_ratio": "",
      "category": "",
      "cooldown_days": "",
      "current_price": 700.73,
      "cyclical_travel_risk_penalty": "",
      "cyclical_travel_risk_tier": "",
      "deferred_sell_reason_code": "",
      "distance_from_ma60": null,
      "event": "MARKET_FILTER",
      "excluded_reason": "",
      "excluded_reason_ko": "",
      "gap_percent": null,
      "high_52w": null,
      "holding_days": "",
      "intraday_range_percent": null,
      "last_sell_date": "",
      "last_sell_reason": "",
      "ma20": 718.57484,
      "ma5": null,
      "ma60": 709.5664433333333,
      "passed": "",
      "position_vs_52w_high_percent": null,
      "previous_day_return": null,
      "profit_rate": "",
      "qty": "",
      "rank": "",
      "reason": "QQQ current price <= QQQ ma20",
      "reason_ko": "QQQ \uc57d\uc138: \ud604\uc7ac\uac00\uac00 20\uc77c\uc120 \uc774\ud558",
      "recent_20d_return": null,
      "recent_3d_return": null,
      "recent_5d_return": null,
      "relative_strength_20_edge": null,
      "relative_strength_60_edge": null,
      "relative_strength_positive": "",
      "remaining_cooldown_days": "",
      "score": "",
      "sell_reason_code": "",
      "share_ratio": "",
      "symbol": "QQQ",
      "timestamp": "2026-07-17T17:36:40",
      "today_return": null,
      "volatility_20": null,
      "volume_spike_ratio": null
    },
    {
      "action": "USE_CANDIDATE_POOL",
      "amount": "",
      "avg_trade_value_20": null,
      "blocked": "",
      "cash": "",
      "cash_ratio": "",
      "category": "",
      "cooldown_days": "",
      "current_price": null,
      "cyclical_travel_risk_penalty": "",
      "cyclical_travel_risk_tier": "",
      "deferred_sell_reason_code": "",
      "distance_from_ma60": null,
      "event": "CANDIDATE_POOL",
      "excluded_reason": "",
      "excluded_reason_ko": "",
      "gap_percent": null,
      "high_52w": null,
      "holding_days": "",
      "intraday_range_percent": null,
      "last_sell_date": "",
      "last_sell_reason": "",
      "ma20": null,
      "ma5": null,
      "ma60": null,
      "passed": "",
      "position_vs_52w_high_percent": null,
      "previous_day_return": null,
      "profit_rate": "",
      "qty": "",
      "rank": "",
      "reason": "candidate pool is fresh",
      "reason_ko": "candidate pool is fresh",
      "recent_20d_return": null,
      "recent_3d_return": null,
      "recent_5d_return": null,
      "relative_strength_20_edge": null,
      "relative_strength_60_edge": null,
      "relative_strength_positive": "",
      "remaining_cooldown_days": "",
      "score": "",
      "sell_reason_code": "",
      "share_ratio": "",
      "symbol": "",
      "timestamp": "2026-07-17T17:36:40",
      "today_return": null,
      "volatility_20": null,
      "volume_spike_ratio": null
    },
    {
      "action": "",
      "amount": "",
      "avg_trade_value_20": 19629168231.39275,
      "blocked": "",
      "cash": "",
      "cash_ratio": "",
      "category": "",
      "cooldown_days": "",
      "current_price": 330.38,
      "cyclical_travel_risk_penalty": 0,
      "cyclical_travel_risk_tier": "none",
      "deferred_sell_reason_code": "",
      "distance_from_ma60": 10.962730152027822,
      "event": "BUY_CANDIDATE",
      "excluded_reason": "",
      "excluded_reason_ko": "",
      "gap_percent": -0.3840844985896763,
      "high_52w": null,
      "holding_days": "",
      "intraday_range_percent": 1.817443494024018,
      "last_sell_date": "",
      "last_sell_reason": "",
      "ma20": 305.34925,
      "ma5": 324.659,
      "ma60": 297.73960999999997,
      "passed": true,
      "position_vs_52w_high_percent": null,
      "previous_day_return": 1.7587786259541938,
      "profit_rate": "",
      "qty": "",
      "rank": 1,
      "reason": "passed",
      "reason_ko": "\ub9e4\uc218 \uc870\uac74 \ud1b5\uacfc",
      "recent_20d_return": 11.633721912485218,
      "recent_3d_return": 4.929174871371389,
      "recent_5d_return": 4.776100469364453,
      "relative_strength_20_edge": 10.680782110971576,
      "relative_strength_60_edge": 12.208060087843597,
      "relative_strength_positive": true,
      "remaining_cooldown_days": "",
      "score": 105,
      "score_breakdown": {
        "avg_trade_value_20": {
          "points": 10,
          "reason": "20-day average trade value >= 1,000,000,000"
        },
        "current_price_above_ma20": {
          "points": 20,
          "reason": "current price > ma20"
        },
        "distance_from_ma60": {
          "points": 10,
          "reason": "distance from ma60 <= 20%"
        },
        "ma_alignment": {
          "points": 30,
          "reason": "ma5 > ma20 > ma60"
        },
        "recent_5d_return": {
          "points": 15,
          "reason": "recent 5-day return <= 5%"
        },
        "relative_strength_vs_qqq": {
          "points": 10,
          "reason": "20/60-day relative strength vs QQQ is positive"
        },
        "volatility_20": {
          "points": 10,
          "reason": "20-day volatility <= 5%"
        }
      },
      "sell_reason_code": "",
      "share_ratio": "",
      "symbol": "AAPL",
      "timestamp": "2026-07-17T17:36:44",
      "today_return": -0.8641901218268022,
      "volatility_20": 2.307965083962848,
      "volume_spike_ratio": 0.9609372987933257
    },
    {
      "action": "NO_BUY",
      "amount": "",
      "avg_trade_value_20": null,
      "blocked": "",
      "cash": "",
      "cash_ratio": "",
      "category": "",
      "cooldown_days": "",
      "current_price": null,
      "cyclical_travel_risk_penalty": "",
      "cyclical_travel_risk_tier": "",
      "deferred_sell_reason_code": "",
      "distance_from_ma60": null,
      "event": "BUY_CHECK",
      "excluded_reason": "",
      "excluded_reason_ko": "",
      "gap_percent": null,
      "high_52w": null,
      "holding_days": "",
      "intraday_range_percent": null,
      "last_sell_date": "",
      "last_sell_reason": "",
      "ma20": null,
      "ma5": null,
      "ma60": null,
      "passed": "",
      "position_vs_52w_high_percent": null,
      "previous_day_return": null,
      "profit_rate": "",
      "qty": "",
      "rank": "",
      "reason": "no candidate",
      "reason_ko": "\ub9e4\uc218 \ud6c4\ubcf4 \uc5c6\uc74c",
      "recent_20d_return": null,
      "recent_3d_return": null,
      "recent_5d_return": null,
      "relative_strength_20_edge": null,
      "relative_strength_60_edge": null,
      "relative_strength_positive": "",
      "remaining_cooldown_days": "",
      "score": "",
      "sell_reason_code": "",
      "share_ratio": "",
      "symbol": "",
      "timestamp": "2026-07-17T17:36:45",
      "today_return": null,
      "volatility_20": null,
      "volume_spike_ratio": null
    },
    {
      "action": "NO_BUY",
      "amount": 0,
      "avg_trade_value_20": 19629168231.39275,
      "blocked": "",
      "cash": 136.11,
      "cash_ratio": "",
      "category": "",
      "cooldown_days": "",
      "current_price": 330.38,
      "cyclical_travel_risk_penalty": 0,
      "cyclical_travel_risk_tier": "none",
      "deferred_sell_reason_code": "",
      "distance_from_ma60": 10.962730152027822,
      "event": "BUY_CANDIDATE_REJECTED",
      "excluded_reason": "",
      "excluded_reason_ko": "",
      "gap_percent": -0.3840844985896763,
      "high_52w": null,
      "holding_days": "",
      "intraday_range_percent": 1.817443494024018,
      "last_sell_date": "",
      "last_sell_reason": "",
      "ma20": 305.34925,
      "ma5": 324.659,
      "ma60": 297.73960999999997,
      "passed": true,
      "position_vs_52w_high_percent": null,
      "previous_day_return": 1.7587786259541938,
      "profit_rate": "",
      "qty": "",
      "rank": 1,
      "reason": "candidate is not affordable with available cash",
      "reason_ko": "\uc0ac\uc6a9 \uac00\ub2a5 \ud604\uae08\uc73c\ub85c \ub9e4\uc218 \ubd88\uac00",
      "recent_20d_return": 11.633721912485218,
      "recent_3d_return": 4.929174871371389,
      "recent_5d_return": 4.776100469364453,
      "relative_strength_20_edge": 10.680782110971576,
      "relative_strength_60_edge": 12.208060087843597,
      "relative_strength_positive": true,
      "remaining_cooldown_days": "",
      "score": 105,
      "score_breakdown": {
        "avg_trade_value_20": {
          "points": 10,
          "reason": "20-day average trade value >= 1,000,000,000"
        },
        "current_price_above_ma20": {
          "points": 20,
          "reason": "current price > ma20"
        },
        "distance_from_ma60": {
          "points": 10,
          "reason": "distance from ma60 <= 20%"
        },
        "ma_alignment": {
          "points": 30,
          "reason": "ma5 > ma20 > ma60"
        },
        "recent_5d_return": {
          "points": 15,
          "reason": "recent 5-day return <= 5%"
        },
        "relative_strength_vs_qqq": {
          "points": 10,
          "reason": "20/60-day relative strength vs QQQ is positive"
        },
        "volatility_20": {
          "points": 10,
          "reason": "20-day volatility <= 5%"
        }
      },
      "sell_reason_code": "",
      "share_ratio": "",
      "symbol": "AAPL",
      "timestamp": "2026-07-17T17:36:45",
      "today_return": -0.8641901218268022,
      "volatility_20": 2.307965083962848,
      "volume_spike_ratio": 0.9609372987933257
    },
    {
      "action": "",
      "amount": "",
      "avg_trade_value_20": 1031956529.773,
      "blocked": "",
      "cash": "",
      "cash_ratio": "",
      "category": "",
      "cooldown_days": "",
      "current_price": 134.8,
      "cyclical_travel_risk_penalty": 0,
      "cyclical_travel_risk_tier": "none",
      "deferred_sell_reason_code": "",
      "distance_from_ma60": 3.969793741180405,
      "event": "SCAN",
      "excluded_reason": "",
      "excluded_reason_ko": "",
      "gap_percent": 0.9611151870873025,
      "high_52w": null,
      "holding_days": "",
      "intraday_range_percent": 4.430168220134423,
      "last_sell_date": "",
      "last_sell_reason": "",
      "ma20": 129.56,
      "ma5": 132.85399999999998,
      "ma60": 129.65304166666667,
      "passed": false,
      "position_vs_52w_high_percent": null,
      "previous_day_return": 3.4927866362946203,
      "profit_rate": "",
      "qty": "",
      "rank": "",
      "reason": "moving averages are not aligned",
      "reason_ko": "5\uc77c/20\uc77c/60\uc77c \uc774\ub3d9\ud3c9\uade0 \uc815\ubc30\uc5f4 \uc544\ub2d8",
      "recent_20d_return": 7.453168593064974,
      "recent_3d_return": 3.660412180867434,
      "recent_5d_return": 3.8280828776091846,
      "relative_strength_20_edge": 6.527823712269798,
      "relative_strength_60_edge": 5.21512367699618,
      "relative_strength_positive": true,
      "remaining_cooldown_days": "",
      "score": 80,
      "score_breakdown": {
        "avg_trade_value_20": {
          "points": 10,
          "reason": "20-day average trade value >= 1,000,000,000"
        },
        "current_price_above_ma20": {
          "points": 20,
          "reason": "current price > ma20"
        },
        "distance_from_ma60": {
          "points": 15,
          "reason": "distance from ma60 <= 10%"
        },
        "ma_alignment": {
          "points": 0,
          "reason": "moving averages are not aligned"
        },
        "recent_5d_return": {
          "points": 15,
          "reason": "recent 5-day return <= 5%"
        },
        "relative_strength_vs_qqq": {
          "points": 10,
          "reason": "20/60-day relative strength vs QQQ is positive"
        },
        "volatility_20": {
          "points": 10,
          "reason": "20-day volatility <= 5%"
        }
      },
      "sell_reason_code": "",
      "share_ratio": "",
      "symbol": "GILD",
      "timestamp": "2026-07-17T17:36:45",
      "today_return": -1.1005135730007387,
      "volatility_20": 2.15565461266976,
      "volume_spike_ratio": 0.9910272479518214
    },
    {
      "action": "",
      "amount": "",
      "avg_trade_value_20": 19629168231.39275,
      "blocked": "",
      "cash": "",
      "cash_ratio": "",
      "category": "",
      "cooldown_days": "",
      "current_price": 330.38,
      "cyclical_travel_risk_penalty": 0,
      "cyclical_travel_risk_tier": "none",
      "deferred_sell_reason_code": "",
      "distance_from_ma60": 10.962730152027822,
      "event": "SCAN",
      "excluded_reason": "",
      "excluded_reason_ko": "",
      "gap_percent": -0.3840844985896763,
      "high_52w": null,
      "holding_days": "",
      "intraday_range_percent": 1.817443494024018,
      "last_sell_date": "",
      "last_sell_reason": "",
      "ma20": 305.34925,
      "ma5": 324.659,
      "ma60": 297.73960999999997,
      "passed": true,
      "position_vs_52w_high_percent": null,
      "previous_day_return": 1.7587786259541938,
      "profit_rate": "",
      "qty": "",
      "rank": "",
      "reason": "passed",
      "reason_ko": "\ub9e4\uc218 \uc870\uac74 \ud1b5\uacfc",
      "recent_20d_return": 11.633721912485218,
      "recent_3d_return": 4.929174871371389,
      "recent_5d_return": 4.776100469364453,
      "relative_strength_20_edge": 10.680782110971576,
      "relative_strength_60_edge": 12.208060087843597,
      "relative_strength_positive": true,
      "remaining_cooldown_days": "",
      "score": 105,
      "score_breakdown": {
        "avg_trade_value_20": {
          "points": 10,
          "reason": "20-day average trade value >= 1,000,000,000"
        },
        "current_price_above_ma20": {
          "points": 20,
          "reason": "current price > ma20"
        },
        "distance_from_ma60": {
          "points": 10,
          "reason": "distance from ma60 <= 20%"
        },
        "ma_alignment": {
          "points": 30,
          "reason": "ma5 > ma20 > ma60"
        },
        "recent_5d_return": {
          "points": 15,
          "reason": "recent 5-day return <= 5%"
        },
        "relative_strength_vs_qqq": {
          "points": 10,
          "reason": "20/60-day relative strength vs QQQ is positive"
        },
        "volatility_20": {
          "points": 10,
          "reason": "20-day volatility <= 5%"
        }
      },
      "sell_reason_code": "",
      "share_ratio": "",
      "symbol": "AAPL",
      "timestamp": "2026-07-17T17:36:45",
      "today_return": -0.8641901218268022,
      "volatility_20": 2.307965083962848,
      "volume_spike_ratio": 0.9609372987933257
    }
  ],
  "rows": [
    {
      "action": "HOLD",
      "amount": "",
      "avg_trade_value_20": 19629085817.4725,
      "blocked": "",
      "cash": "",
      "cash_ratio": "",
      "category": "",
      "cooldown_days": "",
      "current_price": 330.375,
      "cyclical_travel_risk_penalty": 0,
      "cyclical_travel_risk_tier": "none",
      "deferred_sell_reason_code": "",
      "distance_from_ma60": 10.960988719310416,
      "event": "SELL_CHECK",
      "excluded_reason": "",
      "excluded_reason_ko": "",
      "gap_percent": -0.3840844985896763,
      "high_52w": null,
      "holding_days": 3,
      "intraday_range_percent": 1.817443494024018,
      "last_sell_date": "",
      "last_sell_reason": "",
      "ma20": 305.34975,
      "ma5": 324.661,
      "ma60": 297.73977666666667,
      "passed": "",
      "position_vs_52w_high_percent": null,
      "previous_day_return": 1.7587786259541938,
      "profit_rate": 2.35,
      "qty": "",
      "rank": "",
      "reason": "no sell condition",
      "reason_ko": "\ub9e4\ub3c4 \uc870\uac74 \uc5c6\uc74c",
      "recent_20d_return": 11.632032437911821,
      "recent_3d_return": 4.927586864003053,
      "recent_5d_return": 4.774514778637573,
      "relative_strength_20_edge": 10.68095316079628,
      "relative_strength_60_edge": 12.208397828776718,
      "relative_strength_positive": true,
      "remaining_cooldown_days": "",
      "score": "",
      "score_breakdown": {
        "avg_trade_value_20": {
          "points": 10,
          "reason": "20-day average trade value >= 1,000,000,000"
        },
        "current_price_above_ma20": {
          "points": 20,
          "reason": "current price > ma20"
        },
        "distance_from_ma60": {
          "points": 10,
          "reason": "distance from ma60 <= 20%"
        },
        "ma_alignment": {
          "points": 30,
          "reason": "ma5 > ma20 > ma60"
        },
        "recent_5d_return": {
          "points": 15,
          "reason": "recent 5-day return <= 5%"
        },
        "relative_strength_vs_qqq": {
          "points": 10,
          "reason": "20/60-day relative strength vs QQQ is positive"
        },
        "volatility_20": {
          "points": 10,
          "reason": "20-day volatility <= 5%"
        }
      },
      "sell_reason_code": null,
      "share_ratio": "",
      "symbol": "AAPL",
      "timestamp": "2026-07-17T17:36:39",
      "today_return": -0.8656904518994146,
      "volatility_20": 2.3078666808193207,
      "volume_spike_ratio": 0.9609415198413622
    },
    {
      "action": "",
      "amount": "",
      "avg_trade_value_20": null,
      "blocked": "",
      "cash": "",
      "cash_ratio": "",
      "category": "",
      "cooldown_days": "",
      "current_price": 700.73,
      "cyclical_travel_risk_penalty": "",
      "cyclical_travel_risk_tier": "",
      "deferred_sell_reason_code": "",
      "distance_from_ma60": null,
      "event": "MARKET_FILTER",
      "excluded_reason": "",
      "excluded_reason_ko": "",
      "gap_percent": null,
      "high_52w": null,
      "holding_days": "",
      "intraday_range_percent": null,
      "last_sell_date": "",
      "last_sell_reason": "",
      "ma20": 718.57484,
      "ma5": null,
      "ma60": 709.5664433333333,
      "passed": "",
      "position_vs_52w_high_percent": null,
      "previous_day_return": null,
      "profit_rate": "",
      "qty": "",
      "rank": "",
      "reason": "QQQ current price <= QQQ ma20",
      "reason_ko": "QQQ \uc57d\uc138: \ud604\uc7ac\uac00\uac00 20\uc77c\uc120 \uc774\ud558",
      "recent_20d_return": null,
      "recent_3d_return": null,
      "recent_5d_return": null,
      "relative_strength_20_edge": null,
      "relative_strength_60_edge": null,
      "relative_strength_positive": "",
      "remaining_cooldown_days": "",
      "score": "",
      "sell_reason_code": "",
      "share_ratio": "",
      "symbol": "QQQ",
      "timestamp": "2026-07-17T17:36:40",
      "today_return": null,
      "volatility_20": null,
      "volume_spike_ratio": null
    },
    {
      "action": "USE_CANDIDATE_POOL",
      "amount": "",
      "avg_trade_value_20": null,
      "blocked": "",
      "cash": "",
      "cash_ratio": "",
      "category": "",
      "cooldown_days": "",
      "current_price": null,
      "cyclical_travel_risk_penalty": "",
      "cyclical_travel_risk_tier": "",
      "deferred_sell_reason_code": "",
      "distance_from_ma60": null,
      "event": "CANDIDATE_POOL",
      "excluded_reason": "",
      "excluded_reason_ko": "",
      "gap_percent": null,
      "high_52w": null,
      "holding_days": "",
      "intraday_range_percent": null,
      "last_sell_date": "",
      "last_sell_reason": "",
      "ma20": null,
      "ma5": null,
      "ma60": null,
      "passed": "",
      "position_vs_52w_high_percent": null,
      "previous_day_return": null,
      "profit_rate": "",
      "qty": "",
      "rank": "",
      "reason": "candidate pool is fresh",
      "reason_ko": "candidate pool is fresh",
      "recent_20d_return": null,
      "recent_3d_return": null,
      "recent_5d_return": null,
      "relative_strength_20_edge": null,
      "relative_strength_60_edge": null,
      "relative_strength_positive": "",
      "remaining_cooldown_days": "",
      "score": "",
      "sell_reason_code": "",
      "share_ratio": "",
      "symbol": "",
      "timestamp": "2026-07-17T17:36:40",
      "today_return": null,
      "volatility_20": null,
      "volume_spike_ratio": null
    },
    {
      "action": "NO_BUY",
      "amount": 0,
      "avg_trade_value_20": 19629168231.39275,
      "blocked": "",
      "cash": 136.11,
      "cash_ratio": "",
      "category": "",
      "cooldown_days": "",
      "current_price": 330.38,
      "cyclical_travel_risk_penalty": 0,
      "cyclical_travel_risk_tier": "none",
      "deferred_sell_reason_code": "",
      "distance_from_ma60": 10.962730152027822,
      "event": "BUY_CANDIDATE_REJECTED",
      "excluded_reason": "",
      "excluded_reason_ko": "",
      "gap_percent": -0.3840844985896763,
      "high_52w": null,
      "holding_days": "",
      "intraday_range_percent": 1.817443494024018,
      "last_sell_date": "",
      "last_sell_reason": "",
      "ma20": 305.34925,
      "ma5": 324.659,
      "ma60": 297.73960999999997,
      "passed": true,
      "position_vs_52w_high_percent": null,
      "previous_day_return": 1.7587786259541938,
      "profit_rate": "",
      "qty": "",
      "rank": 1,
      "reason": "candidate is not affordable with available cash",
      "reason_ko": "\uc0ac\uc6a9 \uac00\ub2a5 \ud604\uae08\uc73c\ub85c \ub9e4\uc218 \ubd88\uac00",
      "recent_20d_return": 11.633721912485218,
      "recent_3d_return": 4.929174871371389,
      "recent_5d_return": 4.776100469364453,
      "relative_strength_20_edge": 10.680782110971576,
      "relative_strength_60_edge": 12.208060087843597,
      "relative_strength_positive": true,
      "remaining_cooldown_days": "",
      "score": 105,
      "score_breakdown": {
        "avg_trade_value_20": {
          "points": 10,
          "reason": "20-day average trade value >= 1,000,000,000"
        },
        "current_price_above_ma20": {
          "points": 20,
          "reason": "current price > ma20"
        },
        "distance_from_ma60": {
          "points": 10,
          "reason": "distance from ma60 <= 20%"
        },
        "ma_alignment": {
          "points": 30,
          "reason": "ma5 > ma20 > ma60"
        },
        "recent_5d_return": {
          "points": 15,
          "reason": "recent 5-day return <= 5%"
        },
        "relative_strength_vs_qqq": {
          "points": 10,
          "reason": "20/60-day relative strength vs QQQ is positive"
        },
        "volatility_20": {
          "points": 10,
          "reason": "20-day volatility <= 5%"
        }
      },
      "sell_reason_code": "",
      "share_ratio": "",
      "symbol": "AAPL",
      "timestamp": "2026-07-17T17:36:45",
      "today_return": -0.8641901218268022,
      "volatility_20": 2.307965083962848,
      "volume_spike_ratio": 0.9609372987933257
    },
    {
      "action": "NO_BUY",
      "amount": "",
      "avg_trade_value_20": null,
      "blocked": "",
      "cash": "",
      "cash_ratio": "",
      "category": "",
      "cooldown_days": "",
      "current_price": null,
      "cyclical_travel_risk_penalty": "",
      "cyclical_travel_risk_tier": "",
      "deferred_sell_reason_code": "",
      "distance_from_ma60": null,
      "event": "BUY_CHECK",
      "excluded_reason": "",
      "excluded_reason_ko": "",
      "gap_percent": null,
      "high_52w": null,
      "holding_days": "",
      "intraday_range_percent": null,
      "last_sell_date": "",
      "last_sell_reason": "",
      "ma20": null,
      "ma5": null,
      "ma60": null,
      "passed": "",
      "position_vs_52w_high_percent": null,
      "previous_day_return": null,
      "profit_rate": "",
      "qty": "",
      "rank": "",
      "reason": "no candidate",
      "reason_ko": "\ub9e4\uc218 \ud6c4\ubcf4 \uc5c6\uc74c",
      "recent_20d_return": null,
      "recent_3d_return": null,
      "recent_5d_return": null,
      "relative_strength_20_edge": null,
      "relative_strength_60_edge": null,
      "relative_strength_positive": "",
      "remaining_cooldown_days": "",
      "score": "",
      "sell_reason_code": "",
      "share_ratio": "",
      "symbol": "",
      "timestamp": "2026-07-17T17:36:45",
      "today_return": null,
      "volatility_20": null,
      "volume_spike_ratio": null
    },
    {
      "action": "",
      "amount": "",
      "avg_trade_value_20": 1031956529.773,
      "blocked": "",
      "cash": "",
      "cash_ratio": "",
      "category": "",
      "cooldown_days": "",
      "current_price": 134.8,
      "cyclical_travel_risk_penalty": 0,
      "cyclical_travel_risk_tier": "none",
      "deferred_sell_reason_code": "",
      "distance_from_ma60": 3.969793741180405,
      "event": "SCAN",
      "excluded_reason": "",
      "excluded_reason_ko": "",
      "gap_percent": 0.9611151870873025,
      "high_52w": null,
      "holding_days": "",
      "intraday_range_percent": 4.430168220134423,
      "last_sell_date": "",
      "last_sell_reason": "",
      "ma20": 129.56,
      "ma5": 132.85399999999998,
      "ma60": 129.65304166666667,
      "passed": false,
      "position_vs_52w_high_percent": null,
      "previous_day_return": 3.4927866362946203,
      "profit_rate": "",
      "qty": "",
      "rank": "",
      "reason": "moving averages are not aligned",
      "reason_ko": "5\uc77c/20\uc77c/60\uc77c \uc774\ub3d9\ud3c9\uade0 \uc815\ubc30\uc5f4 \uc544\ub2d8",
      "recent_20d_return": 7.453168593064974,
      "recent_3d_return": 3.660412180867434,
      "recent_5d_return": 3.8280828776091846,
      "relative_strength_20_edge": 6.527823712269798,
      "relative_strength_60_edge": 5.21512367699618,
      "relative_strength_positive": true,
      "remaining_cooldown_days": "",
      "score": 80,
      "score_breakdown": {
        "avg_trade_value_20": {
          "points": 10,
          "reason": "20-day average trade value >= 1,000,000,000"
        },
        "current_price_above_ma20": {
          "points": 20,
          "reason": "current price > ma20"
        },
        "distance_from_ma60": {
          "points": 15,
          "reason": "distance from ma60 <= 10%"
        },
        "ma_alignment": {
          "points": 0,
          "reason": "moving averages are not aligned"
        },
        "recent_5d_return": {
          "points": 15,
          "reason": "recent 5-day return <= 5%"
        },
        "relative_strength_vs_qqq": {
          "points": 10,
          "reason": "20/60-day relative strength vs QQQ is positive"
        },
        "volatility_20": {
          "points": 10,
          "reason": "20-day volatility <= 5%"
        }
      },
      "sell_reason_code": "",
      "share_ratio": "",
      "symbol": "GILD",
      "timestamp": "2026-07-17T17:36:45",
      "today_return": -1.1005135730007387,
      "volatility_20": 2.15565461266976,
      "volume_spike_ratio": 0.9910272479518214
    }
  ],
  "schema_version": 2,
  "updated_at": "2026-07-17T17:36:46.369054+00:00"
}
